CGTasks/__init__.py
CGTasks/graham/__init__.py
CGTasks/graham/builder.py
CGTasks/graham/grader.py
CGTasks/graham/model.py
CGTasks/graham/task.py
CGTasks/kd_tree/__init__.py
CGTasks/kd_tree/builder.py
CGTasks/kd_tree/grader.py
CGTasks/kd_tree/model.py
CGTasks/kd_tree/task.py
CGTasks/quickhull/__init__.py
CGTasks/quickhull/builder.py
CGTasks/quickhull/grader.py
CGTasks/quickhull/model.py
CGTasks/quickhull/task.py
CGTasks-1.1.6.dist-info/METADATA
CGTasks-1.1.6.dist-info/WHEEL
CGTasks-1.1.6.dist-info/top_level.txt
CGTasks-1.1.6.dist-info/RECORD
