Metadata-Version: 2.1
Name: CGTasks
Version: 1.1.6
Home-page: https://github.com/OGKG/CGTasks
Author: Vsevolod Hermaniuk & artandfi (Artem Fisunenko)
Requires-Dist: MarkLib
Requires-Dist: CGLib
